cherre_singer_ingest/__init__.py
cherre_singer_ingest/factories/__init__.py
cherre_singer_ingest/factories/bookmark_factory.py
cherre_singer_ingest/factories/remote_file_uri_factory.py
cherre_singer_ingest/repositories/__init__.py
cherre_singer_ingest/repositories/base_state_repository.py
cherre_singer_ingest/repositories/big_query_ingest_state_repository.py
cherre_singer_ingest/repositories/cloud_sql_ingest_state_repository.py
cherre_singer_ingest/services/__init__.py
cherre_singer_ingest/services/bookmark_service.py
cherre_singer_ingest/services/bq.py
cherre_singer_ingest/services/clean_column_name.py
cherre_singer_ingest/services/common.py
cherre_singer_ingest/services/constants.py
cherre_singer_ingest/services/data_formats.py
cherre_singer_ingest/services/env_var_utils.py
cherre_singer_ingest/services/flatten_object.py
cherre_singer_ingest/services/gcs.py
cherre_singer_ingest/services/get_login_token.py
cherre_singer_ingest/services/run_command.py
cherre_singer_ingest/services/run_custom_image_tap.py
cherre_singer_ingest/services/sftp.py
cherre_singer_ingest/services/stream_writers/__init__.py
cherre_singer_ingest/services/stream_writers/avro_stream_writer.py
cherre_singer_ingest/services/stream_writers/per_stream_writer_results.py
cherre_singer_ingest/services/stream_writers/stream_target.py
cherre_singer_ingest/services/streams/__init__.py
cherre_singer_ingest/services/streams/avro_file_stream.py
cherre_singer_ingest/services/streams/base_file_parsing_tap_stream.py
cherre_singer_ingest/services/streams/base_tap_stream.py
cherre_singer_ingest/services/streams/cached_stream.py
cherre_singer_ingest/services/streams/csv_file_stream.py
cherre_singer_ingest/services/streams/fixed_width_file_stream.py
cherre_singer_ingest/services/streams/json_file_stream.py
cherre_singer_ingest/services/streams/rest_stream.py
cherre_singer_ingest/services/streams/shapefile_file_stream.py
cherre_singer_ingest/services/taps/__init__.py
cherre_singer_ingest-16.6.6.dist-info/WHEEL
cherre_singer_ingest-16.6.6.dist-info/METADATA
cherre_singer_ingest-16.6.6.dist-info/RECORD
