Metadata-Version: 2.1
Name: cherre-singer-ingest
Version: 16.6.6
Summary: Library holding the taps and targets for Cherre ingestion
Author: Mathieson
Author-email: mathieson@cherre.com
Requires-Python: >=3.7,<3.9
Classifier: Programming Language :: Python :: 3
Classifier: Programming Language :: Python :: 3.7
Classifier: Programming Language :: Python :: 3.8
Requires-Dist: aiohttp (>=3.6.2,<4.0.0)
Requires-Dist: cherre-domain (>=9.0.1)
Requires-Dist: cherre-google-clients (>=7.12.0)
Requires-Dist: cherre-types (>=0.5.0)
Requires-Dist: cherre_domain (>=8.12.0)
Requires-Dist: click (>=7.1.2,<8.0.0)
Requires-Dist: fastavro (>=1.3.2,<2.0.0)
Requires-Dist: ijson (>=3.1.1,<4.0.0)
Requires-Dist: openpyxl (==3.0.7)
Requires-Dist: paramiko (>=2.7.2,<3.0.0)
Requires-Dist: pyfarmhash (>=0.2.2,<0.3.0)
Requires-Dist: python-snappy (>=0.6.0,<0.7.0)
Requires-Dist: singer-sdk (==0.1.6)
Requires-Dist: xmltodict (>=0.12.0,<0.13.0)
